bbia_external/__init__.py
bbia_external/core/__init__.py
bbia_external/core/cache.py
bbia_external/core/conf/__init__.py
bbia_external/core/conf/settings.py
bbia_external/core/infra/__init__.py
bbia_external/core/infra/server.py
bbia_external/core/middlewares/__init__.py
bbia_external/core/middlewares/rate_limit.py
bbia_external/modules/__init__.py
bbia_external/modules/lang_process/__init__.py
bbia_external/modules/lang_process/chains.py
bbia_external/modules/lang_process/models/__init__.py
bbia_external/modules/lang_process/models/groq.py
bbia_external/modules/lang_process/prompts/__init__.py
bbia_external/modules/lang_process/prompts/rag.py
bbia_external/modules/social_media/__init__.py
bbia_external/modules/social_media/instagram/__init__.py
bbia_external/modules/social_media/instagram/config.py
bbia_external/modules/storage/__init__.py
bbia_external/modules/storage/pinecone/__init__.py
bbia_external/modules/storage/pinecone/vector_store.py
bbia_external-0.1.0.dist-info/METADATA
bbia_external-0.1.0.dist-info/WHEEL
bbia_external-0.1.0.dist-info/top_level.txt
bbia_external-0.1.0.dist-info/RECORD
